mypypp/__init__.py
mypypp/deprecated.py
mypypp/errorcodes.py
mypypp/py.typed
mypypp-0.1.1.dist-info/LICENSE.md
mypypp-0.1.1.dist-info/METADATA
mypypp-0.1.1.dist-info/WHEEL
mypypp-0.1.1.dist-info/RECORD
