Metadata-Version: 2.1
Name: mypypp
Version: 0.1.1
Summary: Collection of experimental plugins for MyPy.
Home-page: https://github.com/bendabir/mypypp
License: GPL-3.0-or-later
Keywords: mypy,mypy-plugin
Author: Bendabir
Requires-Python: >=3.8,<4.0
Classifier: License :: OSI Approved :: GNU General Public License v3 or later (GPLv3+)
Classifier: Programming Language :: Python :: 3
Classifier: Programming Language :: Python :: 3.8
Classifier: Programming Language :: Python :: 3.9
Classifier: Programming Language :: Python :: 3.10
Classifier: Programming Language :: Python :: 3.11
Classifier: Programming Language :: Python :: 3.12
Requires-Dist: mypy (>=1.9.0,<2.0.0)
Requires-Dist: typing-extensions (>=4.9.0,<5.0.0)
Project-URL: Documentation, https://github.com/Bendabir/mypypp/README.md
Project-URL: Repository, https://github.com/bendabir/mypypp
